pum_def_2/__init__.py
pum_def_2-1.0.8.dist-info/METADATA
pum_def_2-1.0.8.dist-info/WHEEL
pum_def_2-1.0.8.dist-info/top_level.txt
pum_def_2-1.0.8.dist-info/RECORD
