Metadata-Version: 2.2
Name: pum_def_2
Version: 1.0.8
Summary: Utilities for PUM
Home-page: 
Author: USEC
Author-email: karasevich.evg903@gmail.com
Classifier: Programming Language :: Python :: 3.12
Classifier: License :: OSI Approved :: MIT License
Classifier: Operating System :: OS Independent
Requires-Python: >=3.11
Requires-Dist: requests>=2.25.1
Dynamic: author
Dynamic: author-email
Dynamic: classifier
Dynamic: description
Dynamic: description-content-type
Dynamic: keywords
Dynamic: requires-dist
Dynamic: requires-python
Dynamic: summary
